odoo/addons/l10n_it_fatturapa_sale/README.rst
odoo/addons/l10n_it_fatturapa_sale/__init__.py
odoo/addons/l10n_it_fatturapa_sale/__manifest__.py
odoo/addons/l10n_it_fatturapa_sale/i18n/de.po
odoo/addons/l10n_it_fatturapa_sale/i18n/it.po
odoo/addons/l10n_it_fatturapa_sale/i18n/l10n_it_fatturapa_sale.pot
odoo/addons/l10n_it_fatturapa_sale/models/__init__.py
odoo/addons/l10n_it_fatturapa_sale/models/account_move.py
odoo/addons/l10n_it_fatturapa_sale/models/account_move_line.py
odoo/addons/l10n_it_fatturapa_sale/models/related_document.py
odoo/addons/l10n_it_fatturapa_sale/models/sale_order.py
odoo/addons/l10n_it_fatturapa_sale/models/sale_order_line.py
odoo/addons/l10n_it_fatturapa_sale/readme/CONTRIBUTORS.rst
odoo/addons/l10n_it_fatturapa_sale/readme/DESCRIPTION.rst
odoo/addons/l10n_it_fatturapa_sale/security/ir.model.access.csv
odoo/addons/l10n_it_fatturapa_sale/static/description/icon.png
odoo/addons/l10n_it_fatturapa_sale/static/description/index.html
odoo/addons/l10n_it_fatturapa_sale/tests/__init__.py
odoo/addons/l10n_it_fatturapa_sale/tests/test_fatturapa_sale.py
odoo/addons/l10n_it_fatturapa_sale/views/related_document_type_views.xml
odoo/addons/l10n_it_fatturapa_sale/views/sale_order_line_views.xml
odoo/addons/l10n_it_fatturapa_sale/views/sale_order_views.xml
odoo14_addon_l10n_it_fatturapa_sale-14.0.1.1.0.dist-info/METADATA
odoo14_addon_l10n_it_fatturapa_sale-14.0.1.1.0.dist-info/WHEEL
odoo14_addon_l10n_it_fatturapa_sale-14.0.1.1.0.dist-info/top_level.txt
odoo14_addon_l10n_it_fatturapa_sale-14.0.1.1.0.dist-info/RECORD
