Metadata-Version: 2.1
Name: odoo14-addon-l10n_it_fatturapa_sale
Version: 14.0.1.1.0
Summary: Aggiunge alcuni dati per la fatturazione elettronica nell'ordine di vendita
Home-page: https://github.com/OCA/l10n-italy
Author: Agile Business Group, Odoo Community Association (OCA)
Author-email: support@odoo-community.org
License: AGPL-3
Classifier: Programming Language :: Python
Classifier: Framework :: Odoo
Classifier: Framework :: Odoo :: 14.0
Classifier: License :: OSI Approved :: GNU Affero General Public License v3
Requires-Python: >=3.6
Requires-Dist: odoo14-addon-l10n-it-fatturapa
Requires-Dist: odoo<14.1dev,>=14.0a
